object_labeling/__init__.py
object_labeling/client.py
object_labeling/gen_thumbnail.py
object_labeling/gen_toml.py
object_labeling/mesh2usd.py
object_labeling/prompts.py
object_labeling/server.py
object_labeling/utils.py
object_labeling-0.1.0.dist-info/LICENSE
object_labeling-0.1.0.dist-info/METADATA
object_labeling-0.1.0.dist-info/WHEEL
object_labeling-0.1.0.dist-info/top_level.txt
object_labeling-0.1.0.dist-info/RECORD
