Metadata-Version: 2.1
Name: object-labeling
Version: 0.1.0
Summary: Automatic annotation of object assets
Home-page: https://git.galbot.com/robot_base/galbot_sim
Author: Junjie Jia
Author-email: jiajunjie@galbot.com
Classifier: Development Status :: 2 - Pre-Alpha
Classifier: Intended Audience :: Developers
Classifier: Natural Language :: English
Classifier: Programming Language :: Python :: 3
Classifier: Programming Language :: Python :: 3.8
License-File: LICENSE
Requires-Dist: bpy
Requires-Dist: toml
Requires-Dist: click
Requires-Dist: transformers
Requires-Dist: curio
Requires-Dist: mathutils
